dune/harmonizer/__init__.py
dune/harmonizer/constants.py
dune/harmonizer/custom_transforms.py
dune/harmonizer/dunesql/dunepostgres.py
dune/harmonizer/dunesql/dunesql.py
dune/harmonizer/dunesql/optimize.py
dune/harmonizer/dunesql/transform.py
dune/harmonizer/errors.py
dune/harmonizer/schemas.py
dune/harmonizer/table_replacements.py
dune/harmonizer/translate.py
dune_harmonizer-0.34.3.dist-info/LICENSE
dune_harmonizer-0.34.3.dist-info/METADATA
dune_harmonizer-0.34.3.dist-info/WHEEL
dune_harmonizer-0.34.3.dist-info/RECORD
