Metadata-Version: 2.1
Name: dune-harmonizer
Version: 0.34.3
Summary: 
Author: Vegard Stikbakke
Author-email: vegard@dune.com
Requires-Python: >=3.10,<4.0
Classifier: Programming Language :: Python :: 3
Classifier: Programming Language :: Python :: 3.10
Classifier: Programming Language :: Python :: 3.11
Requires-Dist: sqlglot (>=16.2,<17.0)
